<?xml version="1.0"?>
<ArrayOfLastMoves xmlns:xsi="http://www.w3.org/2001/XMLSchema-instance" xmlns:xsd="http://www.w3.org/2001/XMLSchema">
  <LastMoves>
    <Move>revealcell(9, 6)</Move>
    <User>npanuhin</User>
    <DateTime>2022-01-08T18:34:41.7137271+00:00</DateTime>
  </LastMoves>
  <LastMoves>
    <Move>flagcell(8, 6)</Move>
    <User>npanuhin</User>
    <DateTime>2022-01-08T18:32:40.5551079+00:00</DateTime>
  </LastMoves>
  <LastMoves>
    <Move>revealcell(8, 0)</Move>
    <User>npanuhin</User>
    <DateTime>2022-01-08T18:31:25.5976032+00:00</DateTime>
  </LastMoves>
  <LastMoves>
    <Move>flagcell(6, 0)</Move>
    <User>npanuhin</User>
    <DateTime>2022-01-08T18:30:15.4205108+00:00</DateTime>
  </LastMoves>
  <LastMoves>
    <Move>revealcell(7, 0)</Move>
    <User>npanuhin</User>
    <DateTime>2022-01-08T18:29:13.0318717+00:00</DateTime>
  </LastMoves>
  <LastMoves>
    <Move>flagcell(7, 2)</Move>
    <User>npanuhin</User>
    <DateTime>2022-01-08T18:27:32.3101776+00:00</DateTime>
  </LastMoves>
  <LastMoves>
    <Move>flagcell(0, 3)</Move>
    <User>npanuhin</User>
    <DateTime>2022-01-08T18:26:20.2096687+00:00</DateTime>
  </LastMoves>
  <LastMoves>
    <Move>revealcell(0, 5)</Move>
    <User>shpatrickguo</User>
    <DateTime>2022-01-07T23:54:56.6202065+00:00</DateTime>
  </LastMoves>
  <LastMoves>
    <Move>revealcell(0, 4)</Move>
    <User>shpatrickguo</User>
    <DateTime>2021-12-30T20:35:49.4013334+00:00</DateTime>
  </LastMoves>
  <LastMoves>
    <Move>revealcell(0, 6)</Move>
    <User>shpatrickguo</User>
    <DateTime>2021-12-24T19:39:33.0049152+00:00</DateTime>
  </LastMoves>
</ArrayOfLastMoves>